examples/__init__.py
examples/consumer.py
examples/publisher.py
examples/server_manager.py
pyrmq/__init__.py
pyrmq/abstract_queue.py
pyrmq/connection.py
pyrmq/consts.py
pyrmq/consumer.py
pyrmq/delivery.py
pyrmq/misc.py
pyrmq/queue.py
pyrmq/redis_client.py
pyrmq/server_manager.py
python_rmq-0.1.8.dist-info/LICENSE
python_rmq-0.1.8.dist-info/METADATA
python_rmq-0.1.8.dist-info/WHEEL
python_rmq-0.1.8.dist-info/top_level.txt
python_rmq-0.1.8.dist-info/RECORD
