Metadata-Version: 2.1
Name: python-rmq
Version: 0.1.8
Summary: Redis based message queue
Home-page: https://github.com/Forden/pyrmq
Author: Forden
Author-email: forden@forden.me
License: MIT
Platform: UNKNOWN
Requires-Dist: aioredis (<1.4,>=1.3)
Requires-Dist: loguru (~=0.5)
Provides-Extra: fast
Requires-Dist: uvloop (<0.15.0,>=0.14.0) ; extra == 'fast'
